coveo_itertools/__init__.py
coveo_itertools/lookups.py
coveo_itertools/py.typed
coveo_itertools-3.0.dist-info/METADATA
coveo_itertools-3.0.dist-info/WHEEL
coveo_itertools-3.0.dist-info/RECORD
